mrgrain/cdk_esbuild/__init__.py
mrgrain/cdk_esbuild/py.typed
mrgrain/cdk_esbuild/_jsii/__init__.py
mrgrain/cdk_esbuild/_jsii/cdk-esbuild@5.7.11.jsii.tgz
mrgrain_cdk_esbuild-5.7.11.dist-info/LICENSE
mrgrain_cdk_esbuild-5.7.11.dist-info/METADATA
mrgrain_cdk_esbuild-5.7.11.dist-info/WHEEL
mrgrain_cdk_esbuild-5.7.11.dist-info/top_level.txt
mrgrain_cdk_esbuild-5.7.11.dist-info/RECORD
