Metadata-Version: 2.1
Name: mrgrain.cdk-esbuild
Version: 5.7.11
Summary: CDK constructs for esbuild, an extremely fast JavaScript bundler
Home-page: https://github.com/mrgrain/cdk-esbuild
Author: Moritz Kornher<mail@moritzkornher.de>
License: MIT
Project-URL: Source, https://github.com/mrgrain/cdk-esbuild
Classifier: Intended Audience :: Developers
Classifier: Operating System :: OS Independent
Classifier: Programming Language :: JavaScript
Classifier: Programming Language :: Python :: 3 :: Only
Classifier: Programming Language :: Python :: 3.9
Classifier: Programming Language :: Python :: 3.10
Classifier: Programming Language :: Python :: 3.11
Classifier: Typing :: Typed
Classifier: Development Status :: 5 - Production/Stable
Classifier: License :: OSI Approved
Requires-Python: ~=3.9
License-File: LICENSE
Requires-Dist: aws-cdk-lib <3.0.0,>=2.51.0
Requires-Dist: constructs <11.0.0,>=10.0.5
Requires-Dist: jsii <2.0.0,>=1.126.0
Requires-Dist: publication >=0.0.3
Requires-Dist: typeguard ==2.13.3
